setup.py
notsetuptools/__init__.py
notsetuptools.egg-info/PKG-INFO
notsetuptools.egg-info/SOURCES.txt
notsetuptools.egg-info/dependency_links.txt
notsetuptools.egg-info/not-zip-safe
notsetuptools.egg-info/top_level.txt