Metadata-Version: 1.0
Name: notsetuptools
Version: 0.1
Summary: A hack to fix setuptools namespace packages hack.
Home-page: UNKNOWN
Author: David Cramer
Author-email: dcramer@gmail.com
License: UNKNOWN
Platform: UNKNOWN
